genrl/__init__.py
genrl/blockchain/__init__.py
genrl/blockchain/connections.py
genrl/blockchain/coordinator.py
genrl/common/__init__.py
genrl/common/tokenizer_utils.py
genrl/communication/__init__.py
genrl/communication/communication.py
genrl/communication/distributed/__init__.py
genrl/communication/distributed/torch_comm.py
genrl/communication/hivemind/__init__.py
genrl/communication/hivemind/hivemind_backend.py
genrl/communication/local/__init__.py
genrl/communication/local/null_comm.py
genrl/data/__init__.py
genrl/data/data_manager.py
genrl/data/hf_data_manager.py
genrl/data/text_data_managers.py
genrl/examples/__init__.py
genrl/examples/code_generation/__init__.py
genrl/examples/code_generation/proposer.py
genrl/examples/code_generation/proposer_requirements.txt
genrl/examples/code_generation/proposer_service.py
genrl/examples/code_generation/proposer_utils.py
genrl/examples/code_generation/solver_data.py
genrl/examples/code_generation/solver_data_mapper.py
genrl/examples/code_generation/solver_manager.py
genrl/examples/code_generation/solver_rewards.py
genrl/examples/code_generation/solver_utils.py
genrl/examples/multistage_math/__init__.py
genrl/examples/multistage_math/data.py
genrl/examples/multistage_math/reward_utils.py
genrl/examples/multistage_math/rewards.py
genrl/examples/rgym/__init__.py
genrl/examples/rgym/data.py
genrl/examples/rgym/datasets.yaml
genrl/examples/rgym/reward_utils.py
genrl/examples/rgym/rewards.py
genrl/examples/text_to_image/__init__.py
genrl/examples/text_to_image/data.py
genrl/examples/text_to_image/ddpo_trainer.py
genrl/examples/text_to_image/rewards.py
genrl/game/__init__.py
genrl/game/game_manager.py
genrl/logging_utils/__init__.py
genrl/logging_utils/global_defs.py
genrl/logging_utils/ml_logger.py
genrl/logging_utils/system_utils.py
genrl/misc_utils/__init__.py
genrl/misc_utils/name_utils.py
genrl/misc_utils/sandbox_executor.py
genrl/misc_utils/utils.py
genrl/models/__init__.py
genrl/models/moe/__init__.py
gensyn_genrl-0.3.0.dist-info/METADATA
gensyn_genrl-0.3.0.dist-info/WHEEL
gensyn_genrl-0.3.0.dist-info/top_level.txt
gensyn_genrl-0.3.0.dist-info/RECORD
