Metadata-Version: 2.4
Name: gensyn-genrl
Version: 0.3.0
Summary: A General RL framerwork in a swarm environment
Requires-Python: >=3.10
Requires-Dist: torch
Requires-Dist: numpy
Requires-Dist: hydra-core
Requires-Dist: datasets
Requires-Dist: transformers
Requires-Dist: tensorboard
Requires-Dist: wandb
Requires-Dist: requests
Requires-Dist: eth-account
Requires-Dist: web3
Requires-Dist: hivemind
Requires-Dist: psutil
Requires-Dist: msgpack
Requires-Dist: hf-transfer
Provides-Extra: dev
Requires-Dist: black; extra == "dev"
Requires-Dist: isort; extra == "dev"
Requires-Dist: pytest; extra == "dev"
Provides-Extra: examples
Requires-Dist: trl; extra == "examples"
Requires-Dist: diffusers; extra == "examples"
Requires-Dist: langchain-sandbox; extra == "examples"
Requires-Dist: ollama; extra == "examples"
Requires-Dist: peft; extra == "examples"
Requires-Dist: reasoning-gym>=0.1.20; extra == "examples"
